blackjack/__init__.py
blackjack/__main__.py
blackjack/card.py
blackjack/cli.py
blackjack/deck.py
blackjack/demo_ascii_cards.py
blackjack/game.py
blackjack/hand.py
blackjack/input_handler.py
blackjack/player.py
gabrielchaves_blackjack-1.0.5.dist-info/METADATA
gabrielchaves_blackjack-1.0.5.dist-info/WHEEL
gabrielchaves_blackjack-1.0.5.dist-info/entry_points.txt
gabrielchaves_blackjack-1.0.5.dist-info/top_level.txt
gabrielchaves_blackjack-1.0.5.dist-info/RECORD
