Metadata-Version: 2.4
Name: gabrielchaves-blackjack
Version: 1.0.5
Summary: A text-based Blackjack game with ASCII art and smart betting system
Author-email: Gabriel Chaves <gabrielchavesmarques@hotmail.com>
License: MIT
Project-URL: Homepage, https://github.com/GabrielChavesM/blackjack
Project-URL: Issues, https://github.com/GabrielChavesM/blackjack/issues
Keywords: blackjack,game,casino,card-game,ascii,terminal
Classifier: Programming Language :: Python :: 3
Classifier: Programming Language :: Python :: 3.8
Classifier: Programming Language :: Python :: 3.9
Classifier: Programming Language :: Python :: 3.10
Classifier: Programming Language :: Python :: 3.11
Classifier: Programming Language :: Python :: 3.12
Classifier: License :: OSI Approved :: MIT License
Classifier: Operating System :: OS Independent
Classifier: Development Status :: 4 - Beta
Classifier: Intended Audience :: End Users/Desktop
Classifier: Topic :: Games/Entertainment
Requires-Python: >=3.8
Requires-Dist: prompt_toolkit>=3.0.0
